core/__init__.py
core/analyseur.py
core/setup.py
core/simulateur.py
data/__init__.py
docs/__init__.py
docs/conf.py
exceptions/__init__.py
exceptions/exceptions.py
io_utils/__init__.py
io_utils/affichage.py
io_utils/export.py
models/__init__.py
models/reseau.py
models/route.py
models/vehicule.py
simulateur_trafic_yosr_mdemagh-0.1.1.dist-info/licenses/LICENSE
tests/__init__.py
tests/conftest.py
tests/test_reseau.py
tests/test_route.py
tests/test_simulateur.py
tests/test_vehicule.py
simulateur_trafic_yosr_mdemagh-0.1.1.dist-info/METADATA
simulateur_trafic_yosr_mdemagh-0.1.1.dist-info/WHEEL
simulateur_trafic_yosr_mdemagh-0.1.1.dist-info/top_level.txt
simulateur_trafic_yosr_mdemagh-0.1.1.dist-info/RECORD
