Metadata-Version: 2.4
Name: simulateur_trafic_yosr_mdemagh
Version: 0.1.1
Summary: Simulateur de trafic routier
Author: Yosr Mdemagh
Author-email: yosrmdemagh@gmail.com
Requires-Python: >=3.8
License-File: LICENSE
Requires-Dist: matplotlib>=3.10.0
Requires-Dist: pandas>=2.3.0
Requires-Dist: numpy>=2.0.0
Requires-Dist: numba>=0.62.0
Dynamic: author
Dynamic: author-email
Dynamic: description
Dynamic: description-content-type
Dynamic: license-file
Dynamic: requires-dist
Dynamic: requires-python
Dynamic: summary
